env_utils/__init__.py
env_utils/__init__.py.bak
env_utils/compat.py
env_utils/tests.py
env_utils/utils.py
python_env_utils-0.4.1.dist-info/DESCRIPTION.rst
python_env_utils-0.4.1.dist-info/METADATA
python_env_utils-0.4.1.dist-info/metadata.json
python_env_utils-0.4.1.dist-info/RECORD
python_env_utils-0.4.1.dist-info/top_level.txt
python_env_utils-0.4.1.dist-info/WHEEL
